{
  "title": "Buddhism for Kids",
  "slug": "post-1157",
  "date": "2013-09-02",
  "raw_date": "2013-09-02T08:20:54+00:00",
  "source_file": "data\\normalized\\suburbandestiny.com\\root\\__query__\\p\\1157\\index.html",
  "source_url": "http://www.suburbandestiny.com/?p=1157",
  "markdown": "\nSo I paged through \\*all\\* of the items on Amazon with the word “Buddha” in it looking for Buddhist themed toys. Abhidharma (the calculus of Buddhism) is good and all, but it’s not appropriate for toddlers.\n\n\n**Ages 0\\-3**  \n\nBooks, from which they will likely learn English, but not much Buddhism.  \n\nBuddha matroshkas, Japanese Daruma (similar to matrokshka) \\& kekoshi (sometimes called Kannon Kokeshi they are too generic to recognize as Buddhist themed), Buddha plush toys (usually novelty items marketed at adults)\n\n\n**Ages 3\\-12**  \n\nMore books, from which hopefully they will pick up the various factoids about Buddhism.  \n\nDaruma bento boxes– the Daruma man is sort of like a Buddhist “Hello Kitty” that gets slapped onto a million and one products– bento boxes, rice bowls, etc. (The Daruma man is supposed to be Bodhidharma the founder of Zen)\n\n\nThis is the time when dolls and action figures matter. You’d think there would be play toy suitable buddhas, boddhisatvas, monks and the like but… nope. The vast majority of figurines are Buddha’s suitable for bookshelf display– no articulated limbs and they are sitting cross legged. Not a long of figures in “stick\\-pose” (standing, arms at side)– not even playmobile style ones that articulate at the waist (but otherwise are pretty stiff and rigid).\n\n\nI found a few Thai and Burmese puppets– Buddhist monks and the like, but not mass produced– they looked sort of like antiques from a folk art collection.\n\n\n**Toys, but they have to be competitive with mass media toys.**  \n\nAt the moment, Japan seems to have a monopoly on Buddhist pop culture, which portrays esoteric Buddhism– that is the variety we tend to call Tibetan Buddhism, but outside of Tibet, the exact same thing is called esoteric Buddhism. Esoteric Buddhism has gods, myths, magic and personages that act more or less like action movie heros– hence their use in manga and anime. (And the Chinese Shaolin monks\\- they were Buddhists, too, and Zen Buddhists at that– why didn’t anyone tell me during all those Kung Fu movies?)\n\n\nRef\\- [Japanese Esoteric Buddhist figurines](http://www.itsalltrue.net/?p=18247), [Manga](http://www.amazon.com/Buddha-Vol-Kapilavastu-Osamu-Tezuka/dp/193223456X) (from the author of Astroboy)  \n\nRevoltech’s figurines\\-  \n\nAsura, A low ranking demi\\-god of Kamadhatu with several arms.  \n\nTamonten, Guardian of the North, 1 of the 4 Guardian Kings, aka Vaisravana  \n\nKomokutin, Guardian of the West, 1 of the 4 Guardian Kings, aka Virūpākṣa  \n\nZochoten, Guardian of the South, 1 of the 4 Guardian Kings, aka Virūḍhaka  \n\nJirokten, Guardian of the East, 1 of the 4 Guardian Kings, aka Dhṛtarāṣṭra\n\n\nTODO: Look up the corresponding Sanskrit names of the following Buddhist personages, who happen to be available in toy\\-figurine form from Japan.  \n\nTaisyakuten  \n\nZikokuten  \n\nKaruraten  \n\nGobuzyougoten  \n\nSanshitaisyou  \n\nBasusennin  \n\nNaraenkengoou  \n\nBisyazya  \n\nIhachiraou\n\n\n**Age 13\\-20**  \n\nI think this is where one sets examples and tries to be available when topics of philosophy come up.\n\n\n**Toys of uncertain play value:**  \n\nDashboard Buddha – like a bobble head, except its a Buddha on a spring.  \n\nAh My Buddha Figurines – From the semi\\-hentai anime series about a monk in training who is surrounded by sexy lady priestesses.  \n\nNetsuke, traditional \\& not so. These are mostly seated buddhas that are like large figurines, but equally inarticulate at the joints.  \n\nMasks. Some venders are selling this big, adult sized masks that are fairly faithful repros of Buddhist statues.  \n\nBuddhist charms. Tiny figurines \\& the like, mostly Thai, for wearing on a necklace.  \n\nA rubber duck in the shape of a Buddha, Homer Simpson in the shape of a Buddha, etc. Same problem as all the other sitting Buddha statues, they don’t articulate.\n\n\n",
  "markdown_file": "data\\extracted\\posts_markdown\\post-1157.md"
}