{
  "title": "Na’vi word list and link to 1st book",
  "slug": "post-611",
  "date": "2009-12-11",
  "raw_date": "2009-12-11T17:12:50+00:00",
  "source_file": "data\\normalized\\suburbandestiny.com\\root\\__query__\\p\\611\\index.html",
  "source_url": "http://www.suburbandestiny.com/?p=611",
  "markdown": "\n**UPDATE**.   This is the most popular post on my blog.  You probably got here from wikipedia.  The na’vi community is almost entirely on [learnnavi.org](http://learnnavi.org/) where you can find better resources.  This particular page isn’t the best online na’vi word list, it was merely the 2nd.  Also, don’t forget the [Na’vi wikibooks](http://en.wikibooks.org/wiki/Na'vi) pages, which is where the wikipedia article wen t after it grew too large.\n\n\nThis came from someone who copied the word list from the Avatar Guide:  \n\nBuy book here: [Avatar Guide](http://www.amazon.com/Avatar-Confidential-Biological-History-Camerons/dp/0061896756/ref=sr_1_1?ie=UTF8&s=books&qid=1260580282&sr=8-1)  \n\nForum of first poster Dec 9, 09 : [Avatar Forum](http://kcbluesman.websitetoolbox.com/post?id=4013403&highlight=navi+language)\n\n\n\n’ampi\ntouch\n’aw\none\n’awpo\none individual\n’awsi*teng*\ntogether\n’awve\nfirst\n’*e*’al\nworst\n’*e*ko\nattack\n’*e*kong\nbeat (rhythmic)\n’*e*ngeng\nlevel\n’*e*veng\nchild\n’*e*vi\nkid (affectionate form of “child”)\n’ì’awn\nremain, stay\n’ìheyu\nspiral\n’*ìng*lìsì\nEnglish language\n’*i*t\nbit, small amount\n’itan\nson\n’*i*te\ndaughter\n’ok\nremembrance\n’ong\nunfold, blossom\n’*u*pe\nwhat (thing)\n’upxare\nmessage\n\n\na\nwhich, that\näie\nvision\nal*ak*sì\nready\nalìm\nfar away, at a distance\nAmhul\nchild’s name\n*Än*sìt\nchild’s name\napxa\nlarge\natan\nlight\natokiri*na*’\natokirina, seeds of the great tree\nätxäle\nrequest\natxkxe\nland\nau\ndrum (made of skin)\naungia\nsign, omen\nayfo\nthey\naylaru\nto the others (contraction of *aylaberu*)\naynga\nyou\nayoe\nwe (exclusive)\nayoeng\nwe (inclusive)\n\n## E\n\n\n\n*e*an\nblue\n*el*tu\nbrain\n*el*tu si\npay attention, quit goofing off\n*el*tungawng\nbrainworm\nemz*a*’u\npass (a test)\neo\nbefore, in front of\neyk\nlead\n*eyk*tan\nleader\nEyaye\nPlant species (Warbonnet)\n*Ey*wa\n“World spirit” – guiding force and deity (equivalent to Gaia); Eywa PN\n*Ey*wa *nga*hu\ngood\\-bye, Eywa (be with you)\n\n## F\n\n\n\nfa\nwith (by means of)\nfa*he*u\nsmell\nfaketuan\n“Alien” (i.e. non\\-Na’vi)\nfì’u\nthis (thing)\nfìfya\nthis way, like this\nfìkem\nthis (action)\n*fì*po\nthis one (person or thing)\nfì*tseng*(e)\nhere, this place\n*fka*rut\npeel\nfkeu\nmighty\nfko\none\nfmawn\nnews, something to report\nfm*e*tok\ntest\nfmi\ntry\nfnu\nquiet (\\= be quiet)\nfo\nthey\nfpak\nhold off, suspend action\nfpe’\nsend\nfpe*i*o\nchallenge (ceremonial)\nfpi\nfor the sake of\nfpom\nwell\\-being; peace\nfpxafaw\nmedusa (animal)\nfpxäkìm\nenter\nfra’u\neverything\nfrapo\neveryone\nftang\nstop\nfte\nso that\nfteke\nso that not, lest\nfti*a*\nstudy\nftu\nfrom (direction)\nftue\neasy\nftxey\nchoose\nfu\nor\nfya’o\npath, way\nfyape\nhow\nfyawìn*txu*\nguide\n\n## H\n\n\n\nha\nso (or “in that case”)\nhapxì\npart\nhasey\ndone, finished\nhawnu\nprotect, shelter\n*hì*’i\nsmall\n*hi*yìk\nfunny (strange)\nhrrap\ndanger\nhu\nwith (accompaniment)\nhufwe\nwind\nhum\nleave, depart\n\n## I\n\n\n\ni’en\nstringed instrument\n*Ik*ni*ma*ya\nThundering rocks, Stairway to Heaven (floating mountains)\n*ik*ran\nmountain banshee\n*ì*lä (also: ìlä)\nby, via, following\nioang\nanimal, beast\nirayo\nthank you\niveh k’nivi s’dir\nbaby carrier/sling\n\n## K\n\n\n\nka\nacross\nkä\ngo\nkaltxì\nhello\nkä*mak*to\nride out\n*ka*me\nsee (spiritual sense)\nkangay\nvalid\nkaryu\nteacher\n*ka*to\nrhythm\n*kaw*krr\nnever\nkawng\nbad, evil\nkawtu\nno one\nke\nnot\n*ke*’u\nnothing\nkea\nno (before a noun)\n*ke*he\nno\n*kel*ku\nhome\nkelku si\nlive, dwell\nKelutrel\nHometree (tree for living in)\nkempe\nwhat (action)\n*ke*nong\nmodel, represent, exemplify\n*ke*rusey\ndead\n*ke*tuwong\nalien\n*ke*wong\nalien\nke*ye*’ung\ninsanity\nkì’ong\nspecies of fruit or vegetable\nkifkey\nworld (physical, solid)\nkìm\nspin\nkin\nneed\n*ki*nä\nseven\nkinam\nleg\nki*nam*til\nknee\nkìng\nthread\nkip\namong\nkì*te*’e\nservice\nkìye*va*me\ngood\\-bye, see you again soon\nkllfriyo’\nbe responsible\nkll*ku*lat\ndig up\nkllkxem\nstand\nkll*pxìl*tu\nterritory\nkllte\nground\nkrr\ntime\nkrrnekx\ntake/consume time\nkrrpe\nwhen\n*kun*sìp\ngunship\nkurakx\ndrive out\nkxam\nmiddle, midpoint\n*kxam*tseng\ncenter (or place in the middle)\n*kxang*angang\nboom\nkxanì\nforbidden\nkxawm\nperhaps, maybe\n*kxe*ner\nspecies of fruit or vegetable\n*kxe*tse\ntail\n\n## L\n\n\n\n*la*he\nother\nlam\nseem, appear\n*la*po\nother one (person or thing)\n*la*tem\nchange\nlaw\nclear, certain\nlehrrap\ndangerous\nLenay’ga\nSlinger (predatory creature)\nlertu\ncolleague\nlì’u\nword\nlok\nclose to\nlonu\nrelease, let go\n*lrr*tok\nsmile\nlu\nbe (am, is, are)\nlumpe\nwhy\n\n## M\n\n\n\nmakto\nride\nmawey\ncalm\n*me*fo\nthey (those two)\nme*na*ri\neyes (two)\nme*u*ia\nhonor\nmeyp\nweak\nmì\nin\n*mik*yun\near\nmìn\nturn\nmìso\naway (position)\nmll*te*\nagree\nmoe\nwe two (exclusive)\nmokri\nvoice\nmuiä\nproper, fair, right\nmun’*i*\ncut\n*mu*ne\ntwo\n*mu*nge\ntake, bring\nmuntxa\nmated\n\n## N\n\n\n\nna\nlike, as\n*na*’rìng\nforest\nNa’vi\nthe People (name for themselves)\nnang\nparticle for surprise or exclamation\n*nan*tang\nviperwolf\n*na*ri\neye\nnari si\nwatch out, be careful\nnawm\ngreat, noble\nne\nto (direction)\nne kllte!\nget down! (literally, “to the ground!”)\nne’ìm\nback (direction)\nnekx\nburn, consume\nneto\naway (direction)\nneu\nwant\nnga\nyou\nngawng\nworm\nngay\ntrue\nngenga\nyou (honorific form)\nngop\ncreate\nnì’aw\nonly\nnì’*aw*tu\nalone (as one person)\nnì’*aw*ve\nfirst\nnì’it\nsmall amount, a bit\nnì’ul\nmore\nniä\ngrab\nNìayoeg\nlike us (pronounced nay*weng*)\nnì*ftu*e\neasily\nnì*ftxa*vang\npassionately, with all heart\nnìhawng\ntoo, excessively\nnìltsan\nwell\nnìmun\nagain\nnìn\nlook at\nnìngay\ntruly\nnìtam\nenough\nnìtut\ncontinually\nnìtxan\nmuch\nnìwin\nfast\nnìwotx\nall (of), in toto, completely\n*nu*lkrr\nlonger (time)\nnume\nlearn\n\n## O\n\n\n\n*o*e\nI\noeng\nwe two (you and I)\n*o*he\nI (deferential or ceremonial form)\nolo’\nclan\n*o*lo’*eyk*tan\nclan leader\nOmati*ka*ya\nBlue Flute Clan\n*o*mum\nknow\n*o*ntu\nnose\n\n## P\n\n\n\n*pä*hem\narrive\npak\nparticle for disparagement\n*pa*lu*lu*kan\nDry Mouth Bringer of Fear (Thanator)\npa’li\nDirehorse\npam\nsound\npamtseo\nmusic\npänutìng\npromise (a thing to someone)\npätsì\nbadge\npawm\nask\npe\nwhat (before a noun)\npeyfa\nhow\npehem\nwhat (action)\npehrr\nwhen\npelun\nwhy\npeng\ntell\npeseng\nwhere\npesu\nwho\npe*u*\nwhat (thing)\npey\nwait\npizayu\nancestor\nplltxe\nspeak\npo\nhe, she\npoan\nhe\npo*e*\nshe\n*po*ngu\ngroup of people, party\npxan\nworthy\n*pxa*sul\nfresh, appealing as food\npxay\nmany\npxel\nlike, as\npxi\nsharp\npxun\narm\npxuntil\nelbow\n\n## R\n\n\n\nrä’ä\ndo not\nral\nmeaning\nralpeng\ninterpret\nRalu\nchild’s name\nrawke\nalarm cry\n*re*nu\npattern\nrey\nlive\nrikx\nmove, shift position\nrim\nyellow\nrina’\nseed\nriti\nstingbat\nrol\nsing\n*ron*sem\nmind\nrutxe\nplease\n\n## S\n\n\n\nsa’nok\nmother\nsan\nsaying; quote\nsa’nu\nmommy\nsä*nu*me\nteaching, instruction\nsat\nthat (after *ftu* only)\nsempu\ndaddy\n*sem*pul\nfather\nset\nnow\nsevin\npretty\nseyri\nlip\n*se*ze\nblue flower\nsi\ndo, make\nsì\nand\nsìk\nunquote\nsìl*ron*sem\nclever (thing)\nsìltsan\ngood\nska’a\ndestroy\nskxawng\nmoron\nslä\nbut\nslu\nbecome\nsngä’i\nbegin, start\n*sngä*’ikrr\nbeginning, start time\n*snu*mìna\ndim (of a person)\nsom\nhot\nspe’*e*\ncapture\nspe’*e*tu\ncaptive\n*srak*(e)\nmarker for yes\\-no questions\nsrane\nyes\nsreu\ndance\nsrung\nhelp, assistance\nsteftxaw\nexamine\nstum\nalmost\nsutx\ntrack, lock up\nswaw\nmoment\nswirä\ncreature\nswizaw\narrow\nswok\nsacred\nswotu\nsacred place\nsyaw\ncall\n\n## T\n\n\n\nta\nfrom (various uses)\nta’em\nfrom above\ntäftxu\nweave\ntä*ftxu*yu\nweaver\ntakuk\nstrike\n*tal*i*o*ang\nsturmbeest\ntam\nsuffice, “do”\ntangek\ntrunk (of a tree)\ntan*hì*\nstar\n*ta*ron\nhunt\n*ta*ronyu\nhunter\ntaw\nsky\ntawng\ndive\ntawng\nduck\n*Taw*tute\nSky Person\nte\nparticle used in full names\ntelem\ncord\ntengfya\nas (\\= same way as)\nteng*krr*\nwhile (\\= same time as)\n*ter*kup\ndie\nte*swo*tìng\ngrant\nteya\nfull\nteylu\nbeetle larva(e)\ntìf*me*tok\ntest\ntìftang\nstopping\ntì*haw*nu\nprotection\ntìkawng\nevil\ntì*ke*nong\nexample\ntìkin\nneed\ntil\njoint, hinge\ntìng\ngive\ntìng *mik*yun\nlisten (usually pronounced: tìm *mik*yun)\ntìng *na*ri\nlook (usually pronounced: tìn *na*ri)\ntìngay\ntruth\ntìran\nwalk\nti*re*a\nspirit\ntir*e*a*fya*’o\nspirit path\ntir*e*ai*o*ang\nspirit animal\ntìrey\nlife\ntìrol\nsong\ntìtxur\nstrength\nto\nthan; comparative mark\ntok\nbe at, occupy a space\n*tok*tor\ndoctor\ntokx\nbody\ntompa\nrain\n*to*ruk\nlast shadow (great leonopteryx)\ntrr\nday\ntsa’u\nthat (thing\nTsa*hay*lu\nbond (neural connection)\n*Tsa*hìk\nmatriarch\ntsakem\nthat (action)\ntsakrr\nthen, at that time\ntsam\nwar\n*tsam*pongu\nwar party\n*tsam*siyu\nwarrior\ntsap’*a*lute\napology\ntsat\nthat (as object)\ntsatseng\nthere, that place\ntsatu\nthat person\ntsawke\nsun\ntsawl\nbig (in stature)\ntse’a\nsee (physical sense)\ntseng(e)\nplace\ntsengpe\nwhere\ntseo\nart\ntsìng\nfour\ntsìvol\nthirty\\-two (octal: 40\\)\ntsko\nbow (weapon)\ntsko swizaw\nbow and arrow\ntskxe\nrock, stone\ntskxekeng\ntraining, exercise\ntslam\nunderstand\ntsleng\nfalse\ntslolam\nGot it. I understand.\ntsmuk, *tsmuk*tu\nsibling\ntsmukan\nbrother\ntsmuke\nsister\ntsnì\nthat\ntspang\nkill\ntsranten\nmatter, be of import\ntsteu\nbrave\ntsun\ncan, be able\ntswayon\nfly\ntsyal\nwing\ntuk*ru*\nspear\ntul\nrun\ntung\nallow\n*tu*pe\nwho\n*tu*te\nperson\ntute*an*\nmale (person)\ntute*e*\nfemale (person)\ntxan\ngreat (in quantity); much\n*txan*tslusam\nwise, much\\-knowing\ntxe’lan\nheart\ntxele\nmatter (subject)\ntxen\nawake\ntxep\nfire\ntxey\nhalt\ntxìm\nbutt, rear end\ntxìng\nleave, abandon\ntxo\nif\ntxoa\nforgiveness\n*txo*kefyaw\nif not, or else\ntxon\nnight\ntxopu\nfear\ntxum\npoison\ntxur\nstrong\n\n## U\n\n\n\n*u*lte\nand\nultxa\nmeeting\n*u*nil\ndream\n*U*niltaron\nDream Hunt\nuniltì*ran*tokx\navatar; dreamwalker body\nuniltì*ran*yu\ndreamwalker\nutral\ntree\n*U*tral Ay*mok*riyä\nTree of Voices\n\n## V\n\n\n\nvirä\nspread, proliferate\nvofu\nsixteen\n*vrr*tep\ndemon\nvul\nbranch (of a tree)\n\n## W\n\n\n\nway\nsong\n*way*telem\nsongchord\nwintxu\nshow\nwrrpa\noutside\nwutso\ndinner, served meal\n\n## Y\n\n\n\n*ye*’rìn\nsoon\n*Ye*rik\nhexapede\nyey\nstraight\nyìm\nbind\nyol\nlong (of time)\nyom\neat\n*yom*tìng\nfeed\nyur\nwash\n\n## Z\n\n\n\nza’*ä*rìp\npull\n*za*’u\ncome\nza*mu*nge\nbring\nzekwä\nfinger\nzene\nmust\n*zì*sìt\nyear\nzong\nsave\nzongtseng\nsafe place, refuge\nzop*lo*\noffence, insult\n\n",
  "markdown_file": "data\\extracted\\posts_markdown\\post-611.md"
}