{
  "title": "Mister SQL | The other half of MS SQL",
  "slug": "post-819",
  "date": "2015-12-03",
  "raw_date": "2015-12-03T13:04:08+00:00",
  "source_file": "data\\normalized\\suburbandestiny.com\\Tech\\index.html",
  "source_url": "http://tech.wakayos.com/?p=819",
  "markdown": "\n**Features worth searching for:**  \n\nLog\\-by\\-level. E.g. info, warn, verbose, error.  \n\nLog\\-by\\-module/theme. E.g. MyClass, file1\\.js, Data, UI, Validation, etc. Sometimes called “groups” or other things.  \n\nLog\\-errors. Info, warn, verbose are all the same data type, but the error is a complex data type and the work flow differs dramatically from the others.  \n\nLog\\-to\\-different places, e.g. HTML, alert, console, Ajax/Server  \n\nLog\\-formatting. E.g. xml, json, CSV, etc.  \n\nLog\\-correlation. E.g. if you log to 2 places, say a client, server and web\\-service and db, and a transactions passes through all four, can you correlate the log entries?  \n\nLog\\-analysis. E.g. if you generate \\*a lot\\* of log entries, something to search/summarize them would be nice.  \n\nSemantic\\-logging. E.g. logging (arbitrary) structured data as well as strings or a fixed set of fields.  \n\nAnalytics. Page hit counters. (I didn’t search for these)  \n\nFeature Usage. Same, but for applications where feature !\\= page  \n\nConsole. Sometimes as a place to spew log entries, sometimes as a place for interactive execution of code.\n\n\n**Repository Queries:**  \n\n[http://bower.io/search/?q\\=logging](http://bower.io/search/?q=logging) 25 entries right now.  \n\n[http://bower.io/search/?q\\=log](http://bower.io/search/?q=log)  \n\n[http://bower.io/search/?q\\=console](http://bower.io/search/?q=console)\n\n\n[https://www.nuget.org/packages?q\\=javascript\\+logging](https://www.nuget.org/packages?q=javascript+logging) Nuget JS logging libraries.\n\n\n<https://nodejsmodules.org/tags/logging> – Nodejs Repository query\n\n\n**Various Uncategorized Browser\\-Centric Libraries**  \n\n[https://github.com/enoex/Bragi\\-Browser](https://github.com/enoex/Bragi-Browser) category logger (here they are called “groups”)  \n\n[https://github.com/better\\-js\\-logging/console\\-logger](https://github.com/better-js-logging/console-logger) category \\& level logger.  \n\n<https://github.com/latentflip/bows> colorful logging by category  \n\n<https://oaxoa.github.io/Conzole/> Side console.  \n\n[https://github.com/structured\\-log/structured\\-log](https://github.com/structured-log/structured-log) – Serilog/Structured Log  \n\n<http://log4javascript.org/> Log4JavaScript – for people who like the log4x API. As of 2015, appears dated \\& unmaintained.  \n\n[http://www.softwarementors.com/log4js\\-ext/](http://www.softwarementors.com/log4js-ext/) More upto date log4x library. Fancy on screen log.  \n\n<https://github.com/stritti/log4js> A level\\-logger. (Many features are IE only)  \n\n<http://smalljs.org/logging/debug/> Console logger with module filters.  \n\n<http://jsnlog.com/> Client side logger that sends events to popular server side logging libraries (more than just server side node)  \n\n<http://www.songho.ca/misc/logger/logger.html> on screen (HTML) logging overlay  \n\n[https://github.com/cerner/canadarm/](https://github.com/cerner/canadarm/ )   \n\n[https://github.com/FacetsTechnologies/loghound](https://github.com/FacetsTechnologies/loghound )   \n\n<http://jstracer.sourceforge.net/>  \n\n<https://github.com/jbail/lumberjack> Monkeypatches the built\\-in console object.\n\n\n**Microlibraries for Browser**  \n\nThese might not be any smaller than other libraries.  \n\n<https://github.com/bfattori/LogJS> – supports local storage logging.  \n\n[https://github.com/kapilkaisare/sleeper\\-agent](https://github.com/kapilkaisare/sleeper-agent) 4 level logging with an on/off switch at runtime.  \n\n<https://github.com/mattkanwisher/driftwood.js> – 4 level logging with environment switches \\& ajax  \n\n<https://github.com/pimterry/loglevel>. 4 level logging Supports plugins.  \n\n[https://github.com/cowboy/javascript\\-debug/tree/v0\\.4](https://github.com/cowboy/javascript-debug/tree/v0.4) console.log wrapper  \n\n<http://js.jsnlog.com/> Same as JSN Log, but just the JS part, so it’s like a microlibrary.  \n\n<https://github.com/gillesruppert/flog>  \n\n[https://github.com/nhnb/console\\-log](https://github.com/nhnb/console-log) – Polymer/web\\-component style console logging  \n\n<https://github.com/icodeforlove/Console.js> – Polyfill for pretty\\-console display?  \n\n<https://github.com/Couto/groundskeeper> – Build step to remove console.log entries before sending to production.\n\n\n**Abandonware**  \n\n[https://github.com/pockata/blackbird\\-js](https://github.com/pockata/blackbird-js) \\-Abandoned? Not sure what it does.  \n\nNitobiBug \\-Abandoned. If you look long enough you can find websites that serve up the file.\n\n\n**Browser plug ins**  \n\n<http://getfirebug.com/logging> – Firefox centric.\n\n\n**Error Logging**  \n\nError logging is more than a print statement. Generally, at point of error you want to capture all the information that the runtime provides.  \n\n<http://www.stacktracejs.com/> Stacktrace and more.  \n\n[http://openmymind.net/2012/4/4/You\\-Really\\-Should\\-Log\\-Client\\-Side\\-Error/](http://openmymind.net/2012/4/4/You-Really-Should-Log-Client-Side-Error/) Roll your own\n\n\n**Node Loggers (might work in Browser, not sure)**  \n\n[https://github.com/enoex/Bragi\\-Node](https://github.com/enoex/Bragi-Node) (Node Centric)  \n\n<https://www.npmjs.com/package/winston> (Node Centric)  \n\n<https://github.com/jstrace/jstrace> (Node centric)  \n\n[https://nodejs.org/en/blog/module/service\\-logging\\-in\\-json\\-with\\-bunyan/](https://nodejs.org/en/blog/module/service-logging-in-json-with-bunyan/) Bunyan\n\n\n**Commercial Loggers**  \n\nOften a opensource client that talks to a commercial server. No idea if these can work w/o the server component.\n\n\n<https://www.loggly.com/docs/javascript/>  \n\n[https://github.com/loggly/loggly\\-jslogger](https://github.com/loggly/loggly-jslogger ) \n\n\n<https://logentries.com/>  \n\n<https://github.com/logentries/le_js>\n\n\n<https://trackjs.com/>  \n\n<https://github.com/trackjs>\n\n\n<http://jslogger.com/>\n\n\n",
  "markdown_file": "data\\extracted\\posts_markdown\\post-819.md"
}