{
  "title": "Writing the Technical Resume",
  "slug": "post-376",
  "date": "2008-04-19",
  "raw_date": "2008-04-19T11:07:24+00:00",
  "source_file": "data\\normalized\\suburbandestiny.com\\root\\__query__\\p\\376\\index.html",
  "source_url": "http://www.suburbandestiny.com/?p=376",
  "markdown": "\n**Advice culled from [Niniane Wang](http://niniane.org/resume_howto.html)**  \n\n[\\- For a project mention tools used](http://niniane.org/resume_howto.html), problem solved  \n\n\\- Don’t include rinky dink stuff along side impressive accomplishments  \n\n\\- Use metrics, not adjectives (wrote 5000 lines of code vs wrote lots of code, double execution time vs made application perform faster)\n\n\n**Advice from me**  \n\n\\- Don’t list any technologies on your resume you never want to work with again. If you don’t want to get solicitations about COBOL jobs, don’t mention you know what COBOL is. If developers don’t take a stand against legacy code, then we are doing a serious disservice to our customers.  Friends don’t let friends write COBOL.\n\n\n\\- Describe the skills earned at jobs you liked in detail. Describe jobs you didn’t like vaguely. You will be sought out for the job that was described in detail.\n\n\n",
  "markdown_file": "data\\extracted\\posts_markdown\\post-376.md"
}