{
  "title": "The Tokiponasphere",
  "slug": "post-639",
  "date": "2009-12-29",
  "raw_date": "2009-12-29T13:17:37+00:00",
  "source_file": "data\\normalized\\suburbandestiny.com\\root\\__query__\\p\\639\\index.html",
  "source_url": "http://www.suburbandestiny.com/?p=639",
  "markdown": "\nSome of these are URL patterns.  Right now I’m too lazy to turn them into hyperlinks.  List generated by searching for toki pona words (which often are not words in any natural language).  You can search these sites at [lukin](http://www.google.com/cse/home?cx=010530258174171504331:trmsq7cfp8g). (but I probably should change the name to alisa or something like that)\n\n\n`http://www.roboart.it`\n\n\nhttp://blankkor.blogspot.com/\n\n\nlvogel.free.fr/tokipona\n\n\nhttp://kenny.hugi.is/tungumal/articles.php?page\\=view\\&contentId\\=4702809\n\n\nhttp://kalama.rpod.ru/\n\n\nhttp://ingakess.livejournal.com/40990\\.html\n\n\nhttp://ru.wikibooks.org/wiki/%D0%A2%D0%BE%D0%BA%D0%B8%D0%BF%D0%BE%D0%BD%D0%B0\n\n\nhttp://ca.wikibooks.org/wiki/Toki\\_pona\n\n\nhttp://en.tokipona.org\n\n\nhttp://fr.wikibooks.org/wiki/Toki\\_pona\n\n\nhttp://aiki.pbworks.com/English\\+to\\+TP\\+dictionary\n\n\nhttp://www.sinleb.com/tokipona/index.php\n\n\nhttp://news.gmane.org/gmane.culture.language.tokipona\n\n\nhttp://www.unilang.org/viewtopic.php?f\\=85\\&t\\=8360\\&start\\=30\\&st\\=0\\&sk\\=t\\&sd\\=a\\&sid\\=cff309540e3a09162fa03c7bd6b3ea54\n\n\nhttp://forvo.com/languages/x\\-tp/\n\n\nhttp://dedalvs.com/relay/previous/lcc2results/2x.html\n\n\nhttp://forums.tokipona.org\n\n\nhttp://sites.google.com/site/tokiponadave\n\n\nhttp://tokipona.wikia.com\n\n\nhttp://en.wikibooks.org/wiki/Toki\\_Pona\n\n\nhttp://alelipona.blogspot.com/\n\n\nhttp://forvo.com/word/mi\\_toki\\_ala\\_e\\_toki\\_pona/\n\n\nhttp://weblog.masukomi.org/2007/01/13/why\\-you\\-should\\-learn\\-toki\\-pona\n\n\nhttp://anadder.com/toki\\_pona\n\n\nhttp://twitter.com/tokipona\n\n\nhttp://tokipl.wikidot.com\n\n\nhttp://tokilili.shoutem.com/\n\n\nhttp://lltpblog.blogspot.com/\n\n\nhttp://www.conlang.info/relay14/ring\\_d.html\n\n\nhttp://www.osun.org/Toki\\+pona\\-pdf.html\n\n\nhttp://en.wikipedia.org/wiki/Toki\\_Pona\n\n\nhttp://www.tokipona.org/\\*\n\n\nhttp://tokipona.wikia.com/wiki/lipu\\_lawa/\\*\n\n\nhttp://rowa.giso.de/languages/toki\\-pona/\\*\n\n\nhttp://\\*.tokipona.bravehost.com/\n\n\nhttp://tokipona.bravehost.com/\n\n\nhttp://www.omniglot.com/babel/tokipona.htm\n\n\nhttp://community.livejournal.com/tokipona/\n\n\nhttp://tokipona.wikia.com\n\n\nhttp://yohs.livejournal.com/\n\n\nhttp://inamidst.com/services/tokipana\n\n\nhttp://www.omniglot.com/writing/tokipona.htm\n\n\nhttp://www.tokipona.info/\n\n\nhttp://pokipitokipona.free.fr/\n\n\nhttp://pokipitokipona.free.fr/\n\n\nhttp://alinome.net/tokipona/\\*\n\n\nhttp://elzr.com/tokipona/\\*\n\n\nhttp://www.freewebs.com/silverwings\\_88/\\*\n\n\nhttp://bellsouthpwp.net/j/i/jimhenry1973/conlang/tokipona/\\*\n\n\nhttp://dedalvs.free.fr/relay/results/2x.html\n\n\nhttp://www.conlang.info/relay14/toki\\_pona\\_2\\.html\n\n\nhttp://vinokaareva.livejournal.com/\n\n\nhttp://en.wikibooks.org/wiki/Toki\\_Pona/\\*\n\n\nhttp://achiral.blogspot.com/2007/03/toki\\-pona.html\n\n\nhttp://eo.wikipedia.org/wiki/Tokipono\n\n\nwww.tobareinne.com/misc/llengua/tokipona/hangul\\-Vkbd.html  \n\nwww.theiling.de/schrift/tokipona.html  \n\nwww.langmaker.com/db/Toki\\_Pona  \n\nwww.geocities.com/stephentoddpope/tokiponabible.html\n\n\nhttp://ru.wikibooks.org/wiki/%D0%A2%D0%BE%D0%BA%D0%B8%D0%BF%D0%BE%D0%BD%D0%B0\n\n\nhttp://toki\\-pona.narod.ru/\n\n\nde.wikipedia.org/wiki/Toki\\_Pona  \n\nwww.langue\\-internationale.org/tokipona.htm\n\n\nhttp://vicerveza.homeunix.net/\\~viric/tokipona/\n\n\nhttp://sv.wikipedia.org/wiki/Toki\\_Pona\n\n\nhttp://www.hugi.is/tungumal/articles.php?page\\=view\\&contentId\\=4702809\n\n\nhttp://atto.tau.ac.il/\\~oyd11/tau/yerev/tp.html\n\n\nhttp://slawistykalodzka.sns.pl/Numer4/ren/esej8\\.html\n\n\nhttp://ju.qihoo.com/1343415\\.html\n\n\nhttp://asemaen.site.voila.fr/tokipona/\n\n\nhttp://bknight0\\.myweb.uga.edu/toki/text/zompist.html\n\n\nhttp://bknight0\\.myweb.uga.edu/toki/\n\n\nhttp://bknight0\\.myweb.uga.edu/toki/text/zompist.html\n\n\nhttp://ixite.ru/toki\\_pona/\n\n\nhttp://www.wessisc.co.uk/tokipona/\n\n\nhttp://www.marketturns.info/article2140205\\.htm\n\n\nhttp://forums.ryzom.com/forum/showthread.php?t\\=21940\n\n\nhttp://en.wiktionary.org/wiki/Toki\\_Pona\n\n\nhttp://www.deadlybrain.org/projects/tokipona/\n\n\nhttp://www.pineight.com/tokipona/\n\n\nhttp://geocities.com/yohsweb/\n\n\nhttp://tokilili.tumblr.com/\n\n\nhttp://home.claranet.de/tokipona\n\n\nhttp://www.geocities.com/yves\\_prudhomme/toki\\_pona/\n\n\nhttp://www.freewebs.com/tokipona/\n\n\nhttp://janjosa.tumblr.com/\n\n\nhttp://www.flashcardexchange.com/flashcards/view/407419\n\n\nhttp://en.wikipedia.org/wiki/Oligosynthetic\n\n\nhttp://www.deadlybrain.org/projects/tokipona/solfege.php\n\n\nhttp://public.kubsu.ru/atem/tokipona\n\n\nhttp://www.encyclopedian.com/to/Toki\\-Pona\\-language.html\n\n\nhttp://www.lingvisto.org/tokipona/\n\n\nhttp://forfikulo.front.ru/tp.html\n\n\nhttp://www.futurologisch.nl/?p\\=38\n\n\nhttp://www.esperanto.fi/fejo/esperhe/tp/\n\n\nhttp://groups.yahoo.com/group/tokipona/\n\n\nhttp://bknight0\\.myweb.uga.edu/toki/about/\n\n\nhttp://dedalvs.free.fr/relay/results/2x.html\n\n\nhttp://tokipona.blahus.cz/\n\n\nhttp://www.freewebs.com/silverwings\\_88/\n\n\nhttp://www.tokipona.bravehost.com/\n\n\nhttp://www.geocities.com/stephentoddpope/tokiponahome\n\n\nhttp://www.geocities.com/girlinside123/toki.html\n\n\nhttp://anadder.com/toki\\_pona\n\n\nhttp://bknight0\\.myweb.uga.edu/toki/ \\[extract linked pages]  \n\nhttp://inamidst.com/services/tokipana \\[extract linked pages]  \n\nhttp://del.icio.us/tag/toki\\-pona?setcount\\=100 \\[extract linked pages]  \n\nhttp://del.icio.us/tag/tokipona?setcount\\=100 \\[extract linked pages]  \n\nhttp://bellsouthpwp.net/j/i/jimhenry1973/conlang/tokipona/tokipona.htm \\[extract linked pages]  \n\nhttp://danielmacouin.chez\\-alice.fr/langues\\_artificielles/toki\\_pona/toki\\_pona\\_accueil.htm \\[extract linked pages]  \n\nhttp://www.tokipona.org/lipupijanante.html \\[extract linked pages] \n\n\n",
  "markdown_file": "data\\extracted\\posts_markdown\\post-639.md"
}