{
  "title": "Tungsten T3- Usage Update",
  "slug": "post-104",
  "date": "2003-12-29",
  "raw_date": "2003-12-29T17:38:26+00:00",
  "source_file": "data\\normalized\\tech.wakayos.com\\root\\__query__\\m\\200312\\index.html",
  "source_url": "http://tech.wakayos.com/?p=104",
  "markdown": "\nI’ve had it for over a month now and I used it for (roughly in order of importance and frequency):  \n\n1\\) MP3 \\& audio books (while driving and at the gym)  \n\n2\\) Ebooks (especially when on vacation, but sometimes at home or standing in line)  \n\n3\\) Password management  \n\n4\\) Flashlight (the screen is almost bright enough to illuminate a small area)  \n\n5\\) Time of day  \n\n6\\) Phone number (but only once, since my cell has all the numbers I’ve ever needed to call)  \n\n7\\) Family photos, used for showing off\n\n\nSome still unused features include:  \n\nBluetooth  \n\nInfrared  \n\nVoice notes\n\n\nUnderused:  \n\nWriting down anything  \n\nTodo list  \n\nCalendar  \n\nGames  \n\nRecipes (but that is because I’ve hardly been cooking, not because I’ve reverted to paper recipes)\n\n\n",
  "markdown_file": "data\\extracted\\posts_markdown\\post-104.md"
}